{"AED":{"code":"AED","title":"United Arab Emirates Dirham","symbol":"AED","native":"د.إ.‏","thousands_sep":",","decimal_sep":".","symbol_left":true,"space_between":true,"exp":2,"min_amount":"367","max_amount":"3673196"},"AFN":{"code":"AFN","title":"Afghan Afghani","symbol":"AFN","native":"؋","thousands_sep":",","decimal_sep":".","symbol_left":true,"space_between":false,"exp":2,"min_amount":"7764","max_amount":"77649671"},"ALL":{"code":"ALL","title":"Albanian Lek","symbol":"ALL","native":"Lek","thousands_sep":".","decimal_sep":",","symbol_left":false,"space_between":false,"exp":2,"min_amount":"10305","max_amount":"103050258"},"AMD":{"code":"AMD","title":"Armenian Dram","symbol":"AMD","native":"դր.","thousands_sep":",","decimal_sep":".","symbol_left":false,"space_between":true,"exp":2,"min_amount":"52637","max_amount":"526379696"},"ARS":{"code":"ARS","title":"Argentine Peso","symbol":"ARS","native":"$","thousands_sep":".","decimal_sep":",","symbol_left":true,"space_between":true,"exp":2,"min_amount":"9078","max_amount":"90783600"},"AUD":{"code":"AUD","title":"Australian Dollar","symbol":"AU$","native":"$","thousands_sep":",","decimal_sep":".","symbol_left":true,"space_between":false,"exp":2,"min_amount":"128","max_amount":"1283038"},"AZN":{"code":"AZN","title":"Azerbaijani Manat","symbol":"AZN","native":"ман.","thousands_sep":" ","decimal_sep":",","symbol_left":false,"space_between":true,"exp":2,"min_amount":"170","max_amount":"1701093"},"BAM":{"code":"BAM","title":"Bosnia & Herzegovina Convertible Mark","symbol":"BAM","native":"KM","thousands_sep":".","decimal_sep":",","symbol_left":false,"space_between":true,"exp":2,"min_amount":"163","max_amount":"1635050"},"BDT":{"code":"BDT","title":"Bangladeshi Taka","symbol":"BDT","native":"৳","thousands_sep":",","decimal_sep":".","symbol_left":true,"space_between":true,"exp":2,"min_amount":"8481","max_amount":"84814530"},"BGN":{"code":"BGN","title":"Bulgarian Lev","symbol":"BGN","native":"лв.","thousands_sep":" ","decimal_sep":",","symbol_left":false,"space_between":true,"exp":2,"min_amount":"163","max_amount":"1631828"},"BND":{"code":"BND","title":"Brunei Dollar","symbol":"BND","native":"$","thousands_sep":".","decimal_sep":",","symbol_left":true,"space_between":false,"exp":2,"min_amount":"134","max_amount":"1340217"},"BOB":{"code":"BOB","title":"Bolivian Boliviano","symbol":"BOB","native":"Bs","thousands_sep":".","decimal_sep":",","symbol_left":true,"space_between":true,"exp":2,"min_amount":"689","max_amount":"6896627"},"BRL":{"code":"BRL","title":"Brazilian Real","symbol":"R$","native":"R$","thousands_sep":".","decimal_sep":",","symbol_left":true,"space_between":true,"exp":2,"min_amount":"553","max_amount":"5535997"},"CAD":{"code":"CAD","title":"Canadian Dollar","symbol":"CA$","native":"$","thousands_sep":",","decimal_sep":".","symbol_left":true,"space_between":false,"exp":2,"min_amount":"125","max_amount":"1253050"},"CHF":{"code":"CHF","title":"Swiss Franc","symbol":"CHF","native":"CHF","thousands_sep":"'","decimal_sep":".","symbol_left":false,"space_between":true,"exp":2,"min_amount":"92","max_amount":"925510"},"CLP":{"code":"CLP","title":"Chilean Peso","symbol":"CLP","native":"$","thousands_sep":".","decimal_sep":",","symbol_left":true,"space_between":true,"exp":0,"min_amount":"713","max_amount":"7133020"},"CNY":{"code":"CNY","title":"Chinese Renminbi Yuan","symbol":"CN¥","native":"CN¥","thousands_sep":",","decimal_sep":".","symbol_left":true,"space_between":false,"exp":2,"min_amount":"649","max_amount":"6493599"},"COP":{"code":"COP","title":"Colombian Peso","symbol":"COP","native":"$","thousands_sep":".","decimal_sep":",","symbol_left":true,"space_between":true,"exp":2,"min_amount":"355600","max_amount":"3556000000"},"CRC":{"code":"CRC","title":"Costa Rican Colón","symbol":"CRC","native":"₡","thousands_sep":".","decimal_sep":",","symbol_left":true,"space_between":false,"exp":2,"min_amount":"61089","max_amount":"610893283"},"CZK":{"code":"CZK","title":"Czech Koruna","symbol":"CZK","native":"Kč","thousands_sep":" ","decimal_sep":",","symbol_left":false,"space_between":true,"exp":2,"min_amount":"2185","max_amount":"21851600"},"DKK":{"code":"DKK","title":"Danish Krone","symbol":"DKK","native":"kr","thousands_sep":"","decimal_sep":",","symbol_left":false,"space_between":true,"exp":2,"min_amount":"620","max_amount":"6207650"},"DOP":{"code":"DOP","title":"Dominican Peso","symbol":"DOP","native":"$","thousands_sep":",","decimal_sep":".","symbol_left":true,"space_between":false,"exp":2,"min_amount":"5745","max_amount":"57450477"},"DZD":{"code":"DZD","title":"Algerian Dinar","symbol":"DZD","native":"د.ج.‏","thousands_sep":",","decimal_sep":".","symbol_left":true,"space_between":true,"exp":2,"min_amount":"13308","max_amount":"133087167"},"EGP":{"code":"EGP","title":"Egyptian Pound","symbol":"EGP","native":"ج.م.‏","thousands_sep":",","decimal_sep":".","symbol_left":true,"space_between":true,"exp":2,"min_amount":"1570","max_amount":"15707199"},"EUR":{"code":"EUR","title":"Euro","symbol":"€","native":"€","thousands_sep":" ","decimal_sep":",","symbol_left":false,"space_between":true,"exp":2,"min_amount":"83","max_amount":"834785"},"GBP":{"code":"GBP","title":"British Pound","symbol":"£","native":"£","thousands_sep":",","decimal_sep":".","symbol_left":true,"space_between":false,"exp":2,"min_amount":"71","max_amount":"714795"},"GEL":{"code":"GEL","title":"Georgian Lari","symbol":"GEL","native":"GEL","thousands_sep":" ","decimal_sep":",","symbol_left":false,"space_between":true,"exp":2,"min_amount":"332","max_amount":"3325039"},"GTQ":{"code":"GTQ","title":"Guatemalan Quetzal","symbol":"GTQ","native":"Q","thousands_sep":",","decimal_sep":".","symbol_left":true,"space_between":false,"exp":2,"min_amount":"773","max_amount":"7731806"},"HKD":{"code":"HKD","title":"Hong Kong Dollar","symbol":"HK$","native":"$","thousands_sep":",","decimal_sep":".","symbol_left":true,"space_between":false,"exp":2,"min_amount":"775","max_amount":"7758610"},"HNL":{"code":"HNL","title":"Honduran Lempira","symbol":"HNL","native":"L","thousands_sep":",","decimal_sep":".","symbol_left":true,"space_between":true,"exp":2,"min_amount":"2426","max_amount":"24260209"},"HRK":{"code":"HRK","title":"Croatian Kuna","symbol":"HRK","native":"kn","thousands_sep":".","decimal_sep":",","symbol_left":false,"space_between":true,"exp":2,"min_amount":"633","max_amount":"6336013"},"HUF":{"code":"HUF","title":"Hungarian Forint","symbol":"HUF","native":"Ft","thousands_sep":" ","decimal_sep":",","symbol_left":false,"space_between":true,"exp":2,"min_amount":"30485","max_amount":"304850354"},"IDR":{"code":"IDR","title":"Indonesian Rupiah","symbol":"IDR","native":"Rp","thousands_sep":".","decimal_sep":",","symbol_left":true,"space_between":false,"exp":2,"min_amount":"1435100","max_amount":"14351000000"},"ILS":{"code":"ILS","title":"Israeli New Sheqel","symbol":"₪","native":"₪","thousands_sep":",","decimal_sep":".","symbol_left":true,"space_between":true,"exp":2,"min_amount":"330","max_amount":"3307840"},"INR":{"code":"INR","title":"Indian Rupee","symbol":"₹","native":"₹","thousands_sep":",","decimal_sep":".","symbol_left":true,"space_between":false,"exp":2,"min_amount":"7267","max_amount":"72671297"},"ISK":{"code":"ISK","title":"Icelandic Króna","symbol":"ISK","native":"kr","thousands_sep":".","decimal_sep":",","symbol_left":false,"space_between":true,"exp":0,"min_amount":"128","max_amount":"1281497"},"JMD":{"code":"JMD","title":"Jamaican Dollar","symbol":"JMD","native":"$","thousands_sep":",","decimal_sep":".","symbol_left":true,"space_between":false,"exp":2,"min_amount":"14783","max_amount":"147834302"},"JPY":{"code":"JPY","title":"Japanese Yen","symbol":"¥","native":"￥","thousands_sep":",","decimal_sep":".","symbol_left":true,"space_between":false,"exp":0,"min_amount":"108","max_amount":"1086829"},"KES":{"code":"KES","title":"Kenyan Shilling","symbol":"KES","native":"Ksh","thousands_sep":",","decimal_sep":".","symbol_left":true,"space_between":false,"exp":2,"min_amount":"10964","max_amount":"109649804"},"KGS":{"code":"KGS","title":"Kyrgyzstani Som","symbol":"KGS","native":"KGS","thousands_sep":" ","decimal_sep":"-","symbol_left":false,"space_between":true,"exp":2,"min_amount":"8479","max_amount":"84799800"},"KRW":{"code":"KRW","title":"South Korean Won","symbol":"₩","native":"₩","thousands_sep":",","decimal_sep":".","symbol_left":true,"space_between":false,"exp":0,"min_amount":"1130","max_amount":"11309649"},"KZT":{"code":"KZT","title":"Kazakhstani Tenge","symbol":"KZT","native":"₸","thousands_sep":" ","decimal_sep":"-","symbol_left":true,"space_between":false,"exp":2,"min_amount":"41953","max_amount":"419532014"},"LBP":{"code":"LBP","title":"Lebanese Pound","symbol":"LBP","native":"ل.ل.‏","thousands_sep":",","decimal_sep":".","symbol_left":true,"space_between":true,"exp":2,"min_amount":"152069","max_amount":"1520690403"},"LKR":{"code":"LKR","title":"Sri Lankan Rupee","symbol":"LKR","native":"රු.","thousands_sep":",","decimal_sep":".","symbol_left":true,"space_between":true,"exp":2,"min_amount":"19654","max_amount":"196545166"},"MAD":{"code":"MAD","title":"Moroccan Dirham","symbol":"MAD","native":"د.م.‏","thousands_sep":",","decimal_sep":".","symbol_left":true,"space_between":true,"exp":2,"min_amount":"898","max_amount":"8986500"},"MDL":{"code":"MDL","title":"Moldovan Leu","symbol":"MDL","native":"MDL","thousands_sep":",","decimal_sep":".","symbol_left":false,"space_between":true,"exp":2,"min_amount":"1772","max_amount":"17728455"},"MNT":{"code":"MNT","title":"Mongolian Tögrög","symbol":"MNT","native":"MNT","thousands_sep":" ","decimal_sep":",","symbol_left":true,"space_between":false,"exp":2,"min_amount":"284875","max_amount":"2848759265"},"MUR":{"code":"MUR","title":"Mauritian Rupee","symbol":"MUR","native":"MUR","thousands_sep":",","decimal_sep":".","symbol_left":true,"space_between":false,"exp":2,"min_amount":"4014","max_amount":"40149892"},"MVR":{"code":"MVR","title":"Maldivian Rufiyaa","symbol":"MVR","native":"MVR","thousands_sep":",","decimal_sep":".","symbol_left":false,"space_between":true,"exp":2,"min_amount":"1544","max_amount":"15449697"},"MXN":{"code":"MXN","title":"Mexican Peso","symbol":"MX$","native":"$","thousands_sep":",","decimal_sep":".","symbol_left":true,"space_between":false,"exp":2,"min_amount":"2063","max_amount":"20631102"},"MYR":{"code":"MYR","title":"Malaysian Ringgit","symbol":"MYR","native":"RM","thousands_sep":",","decimal_sep":".","symbol_left":true,"space_between":false,"exp":2,"min_amount":"411","max_amount":"4110502"},"MZN":{"code":"MZN","title":"Mozambican Metical","symbol":"MZN","native":"MTn","thousands_sep":",","decimal_sep":".","symbol_left":true,"space_between":false,"exp":2,"min_amount":"7402","max_amount":"74025013"},"NGN":{"code":"NGN","title":"Nigerian Naira","symbol":"NGN","native":"₦","thousands_sep":",","decimal_sep":".","symbol_left":true,"space_between":false,"exp":2,"min_amount":"38100","max_amount":"381000088"},"NIO":{"code":"NIO","title":"Nicaraguan Córdoba","symbol":"NIO","native":"C$","thousands_sep":",","decimal_sep":".","symbol_left":true,"space_between":true,"exp":2,"min_amount":"3515","max_amount":"35150118"},"NOK":{"code":"NOK","title":"Norwegian Krone","symbol":"NOK","native":"kr","thousands_sep":" ","decimal_sep":",","symbol_left":true,"space_between":true,"exp":2,"min_amount":"841","max_amount":"8416525"},"NPR":{"code":"NPR","title":"Nepalese Rupee","symbol":"NPR","native":"नेरू","thousands_sep":",","decimal_sep":".","symbol_left":true,"space_between":false,"exp":2,"min_amount":"11624","max_amount":"116240438"},"NZD":{"code":"NZD","title":"New Zealand Dollar","symbol":"NZ$","native":"$","thousands_sep":",","decimal_sep":".","symbol_left":true,"space_between":false,"exp":2,"min_amount":"138","max_amount":"1383530"},"PAB":{"code":"PAB","title":"Panamanian Balboa","symbol":"PAB","native":"B\/.","thousands_sep":",","decimal_sep":".","symbol_left":true,"space_between":true,"exp":2,"min_amount":"100","max_amount":"1000293"},"PEN":{"code":"PEN","title":"Peruvian Nuevo Sol","symbol":"PEN","native":"S\/.","thousands_sep":",","decimal_sep":".","symbol_left":true,"space_between":true,"exp":2,"min_amount":"369","max_amount":"3692496"},"PHP":{"code":"PHP","title":"Philippine Peso","symbol":"PHP","native":"₱","thousands_sep":",","decimal_sep":".","symbol_left":true,"space_between":false,"exp":2,"min_amount":"4842","max_amount":"48422501"},"PKR":{"code":"PKR","title":"Pakistani Rupee","symbol":"PKR","native":"₨","thousands_sep":",","decimal_sep":".","symbol_left":true,"space_between":false,"exp":2,"min_amount":"15724","max_amount":"157249847"},"PLN":{"code":"PLN","title":"Polish Złoty","symbol":"PLN","native":"zł","thousands_sep":" ","decimal_sep":",","symbol_left":false,"space_between":true,"exp":2,"min_amount":"382","max_amount":"3829351"},"PYG":{"code":"PYG","title":"Paraguayan Guaraní","symbol":"PYG","native":"₲","thousands_sep":".","decimal_sep":",","symbol_left":true,"space_between":true,"exp":0,"min_amount":"6601","max_amount":"66010115"},"QAR":{"code":"QAR","title":"Qatari Riyal","symbol":"QAR","native":"ر.ق.‏","thousands_sep":",","decimal_sep":".","symbol_left":true,"space_between":true,"exp":2,"min_amount":"364","max_amount":"3641025"},"RON":{"code":"RON","title":"Romanian Leu","symbol":"RON","native":"RON","thousands_sep":".","decimal_sep":",","symbol_left":false,"space_between":true,"exp":2,"min_amount":"407","max_amount":"4075401"},"RSD":{"code":"RSD","title":"Serbian Dinar","symbol":"RSD","native":"дин.","thousands_sep":".","decimal_sep":",","symbol_left":false,"space_between":true,"exp":2,"min_amount":"9829","max_amount":"98295421"},"RUB":{"code":"RUB","title":"Russian Ruble","symbol":"RUB","native":"руб.","thousands_sep":" ","decimal_sep":",","symbol_left":false,"space_between":true,"exp":2,"min_amount":"7330","max_amount":"73304902"},"SAR":{"code":"SAR","title":"Saudi Riyal","symbol":"SAR","native":"ر.س.‏","thousands_sep":",","decimal_sep":".","symbol_left":true,"space_between":true,"exp":2,"min_amount":"375","max_amount":"3751225"},"SEK":{"code":"SEK","title":"Swedish Krona","symbol":"SEK","native":"kr","thousands_sep":".","decimal_sep":",","symbol_left":false,"space_between":true,"exp":2,"min_amount":"844","max_amount":"8448620"},"SGD":{"code":"SGD","title":"Singapore Dollar","symbol":"SGD","native":"$","thousands_sep":",","decimal_sep":".","symbol_left":true,"space_between":false,"exp":2,"min_amount":"134","max_amount":"1340290"},"THB":{"code":"THB","title":"Thai Baht","symbol":"฿","native":"฿","thousands_sep":",","decimal_sep":".","symbol_left":true,"space_between":false,"exp":2,"min_amount":"3059","max_amount":"30591983"},"TJS":{"code":"TJS","title":"Tajikistani Somoni","symbol":"TJS","native":"TJS","thousands_sep":" ","decimal_sep":";","symbol_left":false,"space_between":true,"exp":2,"min_amount":"1139","max_amount":"11397270"},"TRY":{"code":"TRY","title":"Turkish Lira","symbol":"TRY","native":"TL","thousands_sep":".","decimal_sep":",","symbol_left":false,"space_between":true,"exp":2,"min_amount":"748","max_amount":"7489497"},"TTD":{"code":"TTD","title":"Trinidad and Tobago Dollar","symbol":"TTD","native":"$","thousands_sep":",","decimal_sep":".","symbol_left":true,"space_between":false,"exp":2,"min_amount":"679","max_amount":"6796974"},"TWD":{"code":"TWD","title":"New Taiwan Dollar","symbol":"NT$","native":"NT$","thousands_sep":",","decimal_sep":".","symbol_left":true,"space_between":false,"exp":2,"min_amount":"2812","max_amount":"28127500"},"TZS":{"code":"TZS","title":"Tanzanian Shilling","symbol":"TZS","native":"TSh","thousands_sep":",","decimal_sep":".","symbol_left":true,"space_between":false,"exp":2,"min_amount":"231900","max_amount":"2319000197"},"UAH":{"code":"UAH","title":"Ukrainian Hryvnia","symbol":"UAH","native":"₴","thousands_sep":" ","decimal_sep":",","symbol_left":false,"space_between":false,"exp":2,"min_amount":"2775","max_amount":"27758216"},"UGX":{"code":"UGX","title":"Ugandan Shilling","symbol":"UGX","native":"USh","thousands_sep":",","decimal_sep":".","symbol_left":true,"space_between":false,"exp":0,"min_amount":"3665","max_amount":"36658445"},"USD":{"code":"USD","title":"United States Dollar","symbol":"$","native":"$","thousands_sep":",","decimal_sep":".","symbol_left":true,"space_between":false,"exp":2,"min_amount":"100","max_amount":1000000},"UYU":{"code":"UYU","title":"Uruguayan Peso","symbol":"UYU","native":"$","thousands_sep":".","decimal_sep":",","symbol_left":true,"space_between":true,"exp":2,"min_amount":"4465","max_amount":"44654935"},"UZS":{"code":"UZS","title":"Uzbekistani Som","symbol":"UZS","native":"UZS","thousands_sep":" ","decimal_sep":",","symbol_left":false,"space_between":true,"exp":2,"min_amount":"1050000","max_amount":"10500000026"},"VND":{"code":"VND","title":"Vietnamese Đồng","symbol":"₫","native":"₫","thousands_sep":".","decimal_sep":",","symbol_left":false,"space_between":true,"exp":0,"min_amount":"23052","max_amount":"230525000"},"YER":{"code":"YER","title":"Yemeni Rial","symbol":"YER","native":"ر.ي.‏","thousands_sep":",","decimal_sep":".","symbol_left":true,"space_between":true,"exp":2,"min_amount":"25040","max_amount":"250403890"},"ZAR":{"code":"ZAR","title":"South African Rand","symbol":"ZAR","native":"R","thousands_sep":",","decimal_sep":".","symbol_left":true,"space_between":true,"exp":2,"min_amount":"1486","max_amount":"14862380"}}